{
	"project-settings": "Projekteinstellungen",
	"ofsketch-settings": "ofSketch Einstellungen",
	"editor-settings": "Editor Einstellungen",
	"keyboard-shortcuts": "Tastaturkürzel",
	"reference-link": "Referenz",
	"forum-link": "Forum",
	"ofxaddons-link": "ofxAddons",
	"bug-report-link": "Fehler melden",
	"upload-media": "Medien hochladen",
	"close": "Schließen",
	"save-changes": "Änderungen speichern",
	"basic": "Basic",
	"advanced": "Erweiterte",
	"keyboard-shortcuts-note": "Hinweis: Der Editor muss für Tastenkombinationen, um richtig zu verhalten ausgewählt werden.",
	"bugs": "Bugs + Probleme",
	"submit-issue": "Fehler melden",
	"version-update": "Versions-Update",
	"new-class": "Neue Klasse",
	"rename-class": "Benennen Klasse",
	"delete-class": "Klasse löschen",
	"create": "Schaffen",
	"rename": "Umbenennen",
	"delete": "Löschen",
	"save": "Sparen",
	"nevermind": "Vergiss es!",
	"new-project": "Neues Projekt",
	"name-project": "Nennen Sie das Projekt",
	"name-project-prompt": "Was würden Sie dieses Projekt nennen mag?",
	"rename-project": "Benennen Projekt",
	"open-project": "Projekt öffnen",
	"delete-project": "Projekt löschen",
	"delete-project-prompt": "Sind Sie sicher, dass Sie dieses Projekt wirklich löschen?",
	"task-queue": "Task Queue",
	"cancel-all": "Alle abbrechen",
	"logger": "Logger",
	"connection-error": "Verbindungsfehler",
	"loading": "Verladung ..."
}